{
  "title": "Historical Orders (deprecated)",
  "id": "ws-auth-historical-orders",
  "description": "Deprecated channel that retrieves past orders.",
  "elements": [
    {
      "type": "CODE",
      "content": {
        "codes": [
          {
            "code": "[\n  CHAN_ID, \n  'hos'\n  [\n    [\n      ID, \n      GID,\n      CID,\n      SYMBOL, \n      MTS_CREATE, \n      MTS_UPDATE, \n      AMOUNT, \n      AMOUNT_ORIG, \n      TYPE,\n      TYPE_PREV,\n      _PLACEHOLDER,\n      _PLACEHOLDER,\n      FLAGS,\n      STATUS,\n      _PLACEHOLDER,\n      _PLACEHOLDER,\n      PRICE,\n      PRICE_AVG,\n      PRICE_TRAILING,\n      PRICE_AUX_LIMIT,\n      _PLACEHOLDER,\n      _PLACEHOLDER,\n      _PLACEHOLDER,\n      NOTIFY, \n      HIDDEN, \n      PLACED_ID,\n      ...\n    ], \n    ...\n  ]\n]",
            "language": "json",
            "name": "Snapshot"
          }
        ],
        "sidebar": true
      }
    }
  ]
}